example_package/__init__.py
example_pkg_gatkin-0.0.3.dist-info/LICENSE
example_pkg_gatkin-0.0.3.dist-info/METADATA
example_pkg_gatkin-0.0.3.dist-info/WHEEL
example_pkg_gatkin-0.0.3.dist-info/top_level.txt
example_pkg_gatkin-0.0.3.dist-info/RECORD
